dr_microservices/__init__.py
dr_microservices/cli.py
dr_microservices/dr_microservices.py
dr_microservices-0.0.1.dist-info/DESCRIPTION.rst
dr_microservices-0.0.1.dist-info/METADATA
dr_microservices-0.0.1.dist-info/RECORD
dr_microservices-0.0.1.dist-info/WHEEL
dr_microservices-0.0.1.dist-info/entry_points.txt
dr_microservices-0.0.1.dist-info/metadata.json
dr_microservices-0.0.1.dist-info/top_level.txt
