Metadata-Version: 2.0
Name: dr-microservices
Version: 0.0.1
Summary: Microservices toolset to design, develop, and test microservices in a unified environment.
Home-page: https://github.com/ryananguiano/dr-microservices
Author: Ryan Anguiano
Author-email: ryan.anguiano@gmail.com
License: MIT license
Keywords: dr-microservices
Platform: UNKNOWN
Classifier: Development Status :: 2 - Pre-Alpha
Classifier: Intended Audience :: Developers
Classifier: License :: OSI Approved :: MIT License
Classifier: Natural Language :: English
Classifier: Programming Language :: Python :: 2
Classifier: Programming Language :: Python :: 2.6
Classifier: Programming Language :: Python :: 2.7
Classifier: Programming Language :: Python :: 3
Classifier: Programming Language :: Python :: 3.3
Classifier: Programming Language :: Python :: 3.4
Classifier: Programming Language :: Python :: 3.5
Requires-Dist: Click (>=6.0)
